Workbook
Name difflat: airports!#REF!
Name difflong: airports!#REF!
Name lat_1: airports!#REF!
Name lat_2: airports!#REF!
Name long_1: airports!#REF!
Name long_2: airports!#REF!
Name R_: airports!#REF!

Sheet airports
A1: IATA | B1: AIRPORT | C1: CITY | D1: STATE | E1: COUNTRY | F1: Description | G1: LATITUDE | H1: LONGITUDE | I1: Elevation_ft | J1: Type | K1: In Survey
A2: ABE | B2: Lehigh Valley International | C2: Allentown | D2: PA | E2: USA | F2: =VLOOKUP(A2,L_AIRPORT!A:B,2) -> Allentown/Bethlehem/Easton, PA: Lehigh Valley International | G2: 40.652363 | H2: -75.440402 | I2: 393 | J2: medium_airport | K2: N
A3: ABI | B3: Abilene Regional | C3: Abilene | D3: TX | E3: USA | F3: =VLOOKUP(A3,L_AIRPORT!A:B,2) -> Abilene, TX: Abilene Regional | G3: 32.41132 | H3: -99.681897 | I3: 1791 | J3: medium_airport | K3: N
A4: ABQ | B4: Albuquerque International | C4: Albuquerque | D4: NM | E4: USA | F4: =VLOOKUP(A4,L_AIRPORT!A:B,2) -> Albuquerque, NM: Albuquerque International Sunport | G4: 35.040222 | H4: -106.60919 | I4: 5355 | J4: medium_airport | K4: N
A5: ABR | B5: Aberdeen Regional | C5: Aberdeen | D5: SD | E5: USA | F5: =VLOOKUP(A5,L_AIRPORT!A:B,2) -> Aberdeen, SD: Aberdeen Regional | G5: 45.449056 | H5: -98.421833 | I5: 1302 | J5: medium_airport | K5: N
A6: ABY | B6: Southwest Georgia Regional | C6: Albany | D6: GA | E6: USA | F6: =VLOOKUP(A6,L_AIRPORT!A:B,2) -> Albany, GA: Southwest Georgia Regional | G6: 31.535515 | H6: -84.194473 | I6: 197 | J6: medium_airport | K6: N
A7: ACK | B7: Nantucket Memorial | C7: Nantucket | D7: MA | E7: USA | F7: =VLOOKUP(A7,L_AIRPORT!A:B,2) -> Nantucket, MA: Nantucket Memorial | G7: 41.253052 | H7: -70.060181 | I7: 47 | J7: medium_airport | K7: N
A8: ACT | B8: Waco Regional | C8: Waco | D8: TX | E8: USA | F8: =VLOOKUP(A8,L_AIRPORT!A:B,2) -> Waco, TX: Waco Regional | G8: 31.611288 | H8: -97.230519 | I8: 516 | J8: medium_airport | K8: N
A9: ACV | B9: Arcata | C9: Arcata Eureka | D9: CA | E9: USA | F9: =VLOOKUP(A9,L_AIRPORT!A:B,2) -> Arcata/Eureka, CA: California Redwood Coast Humboldt County | G9: 40.978115 | H9: -124.10862 | I9: 221 | J9: medium_airport | K9: N
A10: ACY | B10: Atlantic City International | C10: Atlantic City | D10: NJ | E10: USA | F10: =VLOOKUP(A10,L_AIRPORT!A:B,2) -> Atlantic City, NJ: Atlantic City International | G10: 39.457583 | H10: -74.577167 | I10: 75 | J10: medium_airport | K10: N
A11: ADK | B11: Adak | C11: Adak | D11: AK | E11: USA | F11: =VLOOKUP(A11,L_AIRPORT!A:B,2) -> Adak Island, AK: Adak | G11: 51.877964 | H11: -176.64603 | I11: 18 | J11: medium_airport | K11: N
A12: ADQ | B12: Kodiak | C12: Kodiak | D12: AK | E12: USA | F12: =VLOOKUP(A12,L_AIRPORT!A:B,2) -> Kodiak, AK: Kodiak Airport | G12: 57.749968 | H12: -152.49386 | I12: 78 | J12: medium_airport | K12: N
A13: AEX | B13: Alexandria International | C13: Alexandria | D13: LA | E13: USA | F13: =VLOOKUP(A13,L_AIRPORT!A:B,2) -> Alexandria, LA: Alexandria International | G13: 31.327372 | H13: -92.548556 | I13: 89 | J13: medium_airport | K13: N
... A404: YUM | B404: Yuma MCAS-Yuma International | C404: Yuma | D404: AZ | E404: USA | F404: =VLOOKUP(A404,L_AIRPORT!A:B,2) -> Yuma, AZ: Yuma MCAS/Yuma International | G404: 32.656583 | H404: -114.60597 | I404: 213 | J404: medium_airport | K404: N

Sheet L_AIRPORT
A1: Code | B1: Description
A2: 01A | B2: Afognak Lake, AK: Afognak Lake Airport
A3: 03A | B3: Granite Mountain, AK: Bear Creek Mining Strip
A4: 04A | B4: Lik, AK: Lik Mining Camp
A5: 05A | B5: Little Squaw, AK: Little Squaw Airport
A6: 06A | B6: Kizhuyak, AK: Kizhuyak Bay
A7: 07A | B7: Klawock, AK: Klawock Seaplane Base
A8: 08A | B8: Elizabeth Island, AK: Elizabeth Island Airport
A9: 09A | B9: Homer, AK: Augustin Island
A10: 1AK | B10: Mertarvik, AK: Mertarvik Quarry Road Landing Strip
A11: 1B1 | B11: Hudson, NY: Columbia County
A12: 1CA | B12: Rio Vista, CA: Rio Vista Municipal
... A6660: ZZZ | B6660: Unknown Point in Alaska

Sheet Distance Calc
C1: lat | D1: long | E1: R | F1: 6371
A2: Origin | B2: =OFFSET(airports!A1,'Distance Calc'!H2,0,1,1) -> ABQ | C2: =VLOOKUP(B2,airports!A1:H117,7,FALSE) -> 35.040222 | D2: =VLOOKUP(B2,airports!A1:H117,8,FALSE) -> -106.60919 | E2: a | F2: =SIN(ABS(C3-C2)*PI()/180/2)^2+COS(C2*PI()/180)*COS(C3*PI()/180)*SIN(ABS(D3-D2)*PI()/180/2)^2 -> 0.046602396 | H2: 3
A3: Destination | B3: =OFFSET(airports!A1,'Distance Calc'!H3,0,1,1) -> AVP | C3: =VLOOKUP(B3,airports!A1:H117,7,FALSE) -> 41.338149 | D3: =VLOOKUP(B3,airports!A1:H117,8,FALSE) -> -75.724267 | E3: c | F3: =2*ATAN2(SQRT(1-F2),SQRT(F2)) -> 0.43517754 | H3: 29
E4: d | F4: =+F1*F3 -> 2772.5161
D7: Miles | E7: =ROUND(ACOS(COS(RADIANS(90-C2)) * COS(RADIANS(90-C3)) + SIN(RADIANS(90-C2)) * SIN(RADIANS(90-C3)) * COS(RADIANS(D2-D3))) * 3959,1) -> 1722.9
D8: Kilometers | E8: =ROUND(ACOS(COS(RADIANS(90-C2)) * COS(RADIANS(90-C3)) + SIN(RADIANS(90-C2)) * SIN(RADIANS(90-C3)) * COS(RADIANS(D2-D3))) * 6371,1) -> 2772.5
C11: Routes | D11: Orgin | E11: Destination | F11: Distance
D12: ACK | E12: DCA | F12: 650.8
D13: FLL | E13: JFK | F13: 1723.4
D14: FLL | E14: SJU | F14: 1683.7

Sheet Routes
A1: ORIGIN | B1: DEST | C1: Flight Route | D1: LAT1 | E1: LOG1 | F1: LAT2 | G1: LOG2 | H1: Dist(kms) | I1: Dist(miles)
A2: ABE | B2: ATL | C2: ABE - ATL | D2: =VLOOKUP(A2,airports!A:H,7,FALSE) -> 40.652363 | E2: =VLOOKUP(A2,airports!A:H,8,FALSE) -> -75.440402 | F2: =VLOOKUP(B2,airports!A:H,7,FALSE) -> 33.640444 | G2: =VLOOKUP(B2,airports!A:H,8,FALSE) -> -84.426944 | H2: =ROUND(ACOS(COS(RADIANS(90-D2)) * COS(RADIANS(90-F2)) + SIN(RADIANS(90-D2)) * SIN(RADIANS(90-F2)) * COS(RADIANS(E2-G2))) * 6371,1) -> 1113.4 | I2: =ROUND(ACOS(COS(RADIANS(90-D2)) * COS(RADIANS(90-F2)) + SIN(RADIANS(90-D2)) * SIN(RADIANS(90-F2)) * COS(RADIANS(E2-G2))) * 3959,1) -> 691.9
A3: ABE | B3: BNA | C3: ABE - BNA | D3: =VLOOKUP(A3,airports!A:H,7,FALSE) -> 40.652363 | E3: =VLOOKUP(A3,airports!A:H,8,FALSE) -> -75.440402 | F3: =VLOOKUP(B3,airports!A:H,7,FALSE) -> 36.124477 | G3: =VLOOKUP(B3,airports!A:H,8,FALSE) -> -86.678182 | H3: =ROUND(ACOS(COS(RADIANS(90-D3)) * COS(RADIANS(90-F3)) + SIN(RADIANS(90-D3)) * SIN(RADIANS(90-F3)) * COS(RADIANS(E3-G3))) * 6371,1) -> 1100.1 | I3: =ROUND(ACOS(COS(RADIANS(90-D3)) * COS(RADIANS(90-F3)) + SIN(RADIANS(90-D3)) * SIN(RADIANS(90-F3)) * COS(RADIANS(E3-G3))) * 3959,1) -> 683.6
A4: ABE | B4: CLT | C4: ABE - CLT | D4: =VLOOKUP(A4,airports!A:H,7,FALSE) -> 40.652363 | E4: =VLOOKUP(A4,airports!A:H,8,FALSE) -> -75.440402 | F4: =VLOOKUP(B4,airports!A:H,7,FALSE) -> 35.214011 | G4: =VLOOKUP(B4,airports!A:H,8,FALSE) -> -80.943126 | H4: =ROUND(ACOS(COS(RADIANS(90-D4)) * COS(RADIANS(90-F4)) + SIN(RADIANS(90-D4)) * SIN(RADIANS(90-F4)) * COS(RADIANS(E4-G4))) * 6371,1) -> 773.3 | I4: =ROUND(ACOS(COS(RADIANS(90-D4)) * COS(RADIANS(90-F4)) + SIN(RADIANS(90-D4)) * SIN(RADIANS(90-F4)) * COS(RADIANS(E4-G4))) * 3959,1) -> 480.5
A5: ABE | B5: DTW | C5: ABE - DTW | D5: =VLOOKUP(A5,airports!A:H,7,FALSE) -> 40.652363 | E5: =VLOOKUP(A5,airports!A:H,8,FALSE) -> -75.440402 | F5: =VLOOKUP(B5,airports!A:H,7,FALSE) -> 42.212059 | G5: =VLOOKUP(B5,airports!A:H,8,FALSE) -> -83.348836 | H5: =ROUND(ACOS(COS(RADIANS(90-D5)) * COS(RADIANS(90-F5)) + SIN(RADIANS(90-D5)) * SIN(RADIANS(90-F5)) * COS(RADIANS(E5-G5))) * 6371,1) -> 681.4 | I5: =ROUND(ACOS(COS(RADIANS(90-D5)) * COS(RADIANS(90-F5)) + SIN(RADIANS(90-D5)) * SIN(RADIANS(90-F5)) * COS(RADIANS(E5-G5))) * 3959,1) -> 423.5
A6: ABE | B6: FLL | C6: ABE - FLL | D6: =VLOOKUP(A6,airports!A:H,7,FALSE) -> 40.652363 | E6: =VLOOKUP(A6,airports!A:H,8,FALSE) -> -75.440402 | F6: =VLOOKUP(B6,airports!A:H,7,FALSE) -> 26.072583 | G6: =VLOOKUP(B6,airports!A:H,8,FALSE) -> -80.15275 | H6: =ROUND(ACOS(COS(RADIANS(90-D6)) * COS(RADIANS(90-F6)) + SIN(RADIANS(90-D6)) * SIN(RADIANS(90-F6)) * COS(RADIANS(E6-G6))) * 6371,1) -> 1678.5 | I6: =ROUND(ACOS(COS(RADIANS(90-D6)) * COS(RADIANS(90-F6)) + SIN(RADIANS(90-D6)) * SIN(RADIANS(90-F6)) * COS(RADIANS(E6-G6))) * 3959,1) -> 1043
A7: ABE | B7: IAD | C7: ABE - IAD | D7: =VLOOKUP(A7,airports!A:H,7,FALSE) -> 40.652363 | E7: =VLOOKUP(A7,airports!A:H,8,FALSE) -> -75.440402 | F7: =VLOOKUP(B7,airports!A:H,7,FALSE) -> 38.944532 | G7: =VLOOKUP(B7,airports!A:H,8,FALSE) -> -77.45581 | H7: =ROUND(ACOS(COS(RADIANS(90-D7)) * COS(RADIANS(90-F7)) + SIN(RADIANS(90-D7)) * SIN(RADIANS(90-F7)) * COS(RADIANS(E7-G7))) * 6371,1) -> 256.3 | I7: =ROUND(ACOS(COS(RADIANS(90-D7)) * COS(RADIANS(90-F7)) + SIN(RADIANS(90-D7)) * SIN(RADIANS(90-F7)) * COS(RADIANS(E7-G7))) * 3959,1) -> 159.3
A8: ABE | B8: MDT | C8: ABE - MDT | D8: =VLOOKUP(A8,airports!A:H,7,FALSE) -> 40.652363 | E8: =VLOOKUP(A8,airports!A:H,8,FALSE) -> -75.440402 | F8: =VLOOKUP(B8,airports!A:H,7,FALSE) -> 40.193495 | G8: =VLOOKUP(B8,airports!A:H,8,FALSE) -> -76.763404 | H8: =ROUND(ACOS(COS(RADIANS(90-D8)) * COS(RADIANS(90-F8)) + SIN(RADIANS(90-D8)) * SIN(RADIANS(90-F8)) * COS(RADIANS(E8-G8))) * 6371,1) -> 123.1 | I8: =ROUND(ACOS(COS(RADIANS(90-D8)) * COS(RADIANS(90-F8)) + SIN(RADIANS(90-D8)) * SIN(RADIANS(90-F8)) * COS(RADIANS(E8-G8))) * 3959,1) -> 76.5
A9: ABE | B9: MDW | C9: ABE - MDW | D9: =VLOOKUP(A9,airports!A:H,7,FALSE) -> 40.652363 | E9: =VLOOKUP(A9,airports!A:H,8,FALSE) -> -75.440402 | F9: =VLOOKUP(B9,airports!A:H,7,FALSE) -> 41.785983 | G9: =VLOOKUP(B9,airports!A:H,8,FALSE) -> -87.752424 | H9: =ROUND(ACOS(COS(RADIANS(90-D9)) * COS(RADIANS(90-F9)) + SIN(RADIANS(90-D9)) * SIN(RADIANS(90-F9)) * COS(RADIANS(E9-G9))) * 6371,1) -> 1036.6 | I9: =ROUND(ACOS(COS(RADIANS(90-D9)) * COS(RADIANS(90-F9)) + SIN(RADIANS(90-D9)) * SIN(RADIANS(90-F9)) * COS(RADIANS(E9-G9))) * 3959,1) -> 644.1
A10: ABE | B10: MYR | C10: ABE - MYR | D10: =VLOOKUP(A10,airports!A:H,7,FALSE) -> 40.652363 | E10: =VLOOKUP(A10,airports!A:H,8,FALSE) -> -75.440402 | F10: =VLOOKUP(B10,airports!A:H,7,FALSE) -> 33.67975 | G10: =VLOOKUP(B10,airports!A:H,8,FALSE) -> -78.928333 | H10: =ROUND(ACOS(COS(RADIANS(90-D10)) * COS(RADIANS(90-F10)) + SIN(RADIANS(90-D10)) * SIN(RADIANS(90-F10)) * COS(RADIANS(E10-G10))) * 6371,1) -> 834.5 | I10: =ROUND(ACOS(COS(RADIANS(90-D10)) * COS(RADIANS(90-F10)) + SIN(RADIANS(90-D10)) * SIN(RADIANS(90-F10)) * COS(RADIANS(E10-G10))) * 3959,1) -> 518.5
A11: ABE | B11: ORD | C11: ABE - ORD | D11: =VLOOKUP(A11,airports!A:H,7,FALSE) -> 40.652363 | E11: =VLOOKUP(A11,airports!A:H,8,FALSE) -> -75.440402 | F11: =VLOOKUP(B11,airports!A:H,7,FALSE) -> 41.979595 | G11: =VLOOKUP(B11,airports!A:H,8,FALSE) -> -87.904464 | H11: =ROUND(ACOS(COS(RADIANS(90-D11)) * COS(RADIANS(90-F11)) + SIN(RADIANS(90-D11)) * SIN(RADIANS(90-F11)) * COS(RADIANS(E11-G11))) * 6371,1) -> 1050.4 | I11: =ROUND(ACOS(COS(RADIANS(90-D11)) * COS(RADIANS(90-F11)) + SIN(RADIANS(90-D11)) * SIN(RADIANS(90-F11)) * COS(RADIANS(E11-G11))) * 3959,1) -> 652.7
A12: ABE | B12: PGD | C12: ABE - PGD | D12: =VLOOKUP(A12,airports!A:H,7,FALSE) -> 40.652363 | E12: =VLOOKUP(A12,airports!A:H,8,FALSE) -> -75.440402 | F12: =VLOOKUP(B12,airports!A:H,7,FALSE) -> 26.9197 | G12: =VLOOKUP(B12,airports!A:H,8,FALSE) -> -81.996 | H12: =ROUND(ACOS(COS(RADIANS(90-D12)) * COS(RADIANS(90-F12)) + SIN(RADIANS(90-D12)) * SIN(RADIANS(90-F12)) * COS(RADIANS(E12-G12))) * 6371,1) -> 1641.5 | I12: =ROUND(ACOS(COS(RADIANS(90-D12)) * COS(RADIANS(90-F12)) + SIN(RADIANS(90-D12)) * SIN(RADIANS(90-F12)) * COS(RADIANS(E12-G12))) * 3959,1) -> 1020
A13: ABE | B13: PHL | C13: ABE - PHL | D13: =VLOOKUP(A13,airports!A:H,7,FALSE) -> 40.652363 | E13: =VLOOKUP(A13,airports!A:H,8,FALSE) -> -75.440402 | F13: =VLOOKUP(B13,airports!A:H,7,FALSE) -> 39.871953 | G13: =VLOOKUP(B13,airports!A:H,8,FALSE) -> -75.241141 | H13: =ROUND(ACOS(COS(RADIANS(90-D13)) * COS(RADIANS(90-F13)) + SIN(RADIANS(90-D13)) * SIN(RADIANS(90-F13)) * COS(RADIANS(E13-G13))) * 6371,1) -> 88.4 | I13: =ROUND(ACOS(COS(RADIANS(90-D13)) * COS(RADIANS(90-F13)) + SIN(RADIANS(90-D13)) * SIN(RADIANS(90-F13)) * COS(RADIANS(E13-G13))) * 3959,1) -> 54.9
... A6614: RDU | B6614: JAX | C6614: RDU - JAX | D6614: =VLOOKUP(A6614,airports!A:H,7,FALSE) -> 35.877639 | E6614: =VLOOKUP(A6614,airports!A:H,8,FALSE) -> -78.787472 | F6614: =VLOOKUP(B6614,airports!A:H,7,FALSE) -> 30.494056 | G6614: =VLOOKUP(B6614,airports!A:H,8,FALSE) -> -81.687861 | H6614: =ROUND(ACOS(COS(RADIANS(90-D6614)) * COS(RADIANS(90-F6614)) + SIN(RADIANS(90-D6614)) * SIN(RADIANS(90-F6614)) * COS(RADIANS(E6614-G6614))) * 6371,1) -> 656.6 | I6614: =ROUND(ACOS(COS(RADIANS(90-D6614)) * COS(RADIANS(90-F6614)) + SIN(RADIANS(90-D6614)) * SIN(RADIANS(90-F6614)) * COS(RADIANS(E6614-G6614))) * 3959,1) -> 408
A6615: RDU | B6615: JFK | C6615: RDU - JFK
A6616: RDU | B6616: LAS | C6616: RDU - LAS
A6617: RDU | B6617: LAX | C6617: RDU - LAX
A6618: RDU | B6618: LGA | C6618: RDU - LGA
A6619: RDU | B6619: MCI | C6619: RDU - MCI
A6620: RDU | B6620: MCO | C6620: RDU - MCO
A6621: RDU | B6621: MDT | C6621: RDU - MDT
A6622: RDU | B6622: MDW | C6622: RDU - MDW
A6623: RDU | B6623: MIA | C6623: RDU - MIA
A6624: RDU | B6624: MKE | C6624: RDU - MKE
A6625: RDU | B6625: MSN | C6625: RDU - MSN
A6626: RDU | B6626: MSP | C6626: RDU - MSP
... A8286: YUM | B8286: PHX | C8286: YUM - PHX
